labautomation_utils/coordconversion/__init__.py
labautomation_utils/coordconversion/wellplate.py
labautomation_utils-1.0.0.dist-info/LICENSE
labautomation_utils-1.0.0.dist-info/METADATA
labautomation_utils-1.0.0.dist-info/WHEEL
labautomation_utils-1.0.0.dist-info/top_level.txt
labautomation_utils-1.0.0.dist-info/RECORD
